pylestia/README.md
pylestia/__init__.py
pylestia/node_api/__init__.py
pylestia/node_api/blob.py
pylestia/node_api/das.py
pylestia/node_api/fraud.py
pylestia/node_api/header.py
pylestia/node_api/p2p.py
pylestia/node_api/rpc/__init__.py
pylestia/node_api/rpc/abc.py
pylestia/node_api/rpc/executor.py
pylestia/node_api/share.py
pylestia/node_api/state.py
pylestia/types/__init__.py
pylestia/types/blob.py
pylestia/types/common_types.py
pylestia/types/das.py
pylestia/types/errors.py
pylestia/types/header.py
pylestia/types/p2p.py
pylestia/types/share.py
pylestia/types/state.py
pylestia-0.2.1.dist-info/METADATA
pylestia-0.2.1.dist-info/WHEEL
pylestia-0.2.1.dist-info/RECORD
