Metadata-Version: 2.3
Name: pylestia
Version: 0.2.1
Summary: The Python client for working with the Celestia blockchain platform.
License: MIT
Author: Alex Poryadin
Author-email: alexey.poryadin@gmail.com
Requires-Python: >=3.10
Classifier: License :: OSI Approved :: MIT License
Classifier: Operating System :: OS Independent
Classifier: Programming Language :: Python :: 3
Classifier: Programming Language :: Python :: 3.10
Classifier: Programming Language :: Python :: 3.11
Classifier: Programming Language :: Python :: 3.12
Classifier: Programming Language :: Python :: 3.13
Classifier: Programming Language :: Python :: Implementation :: CPython
Classifier: Programming Language :: Rust
Classifier: Topic :: Software Development :: Libraries :: Python Modules
Provides-Extra: validation
Requires-Dist: ajsonrpc
Requires-Dist: async-timeout
Requires-Dist: pydantic (>=2.11.3,<3.0.0) ; extra == "validation"
Requires-Dist: typing-extensions
Requires-Dist: websockets
Project-URL: Repository, https://github.com/Bidon15/pylestia
